chatmof/__init__.py
chatmof/app.py
chatmof/config.py
chatmof/main.py
chatmof/setup_module.py
chatmof/utils.py
chatmof/agents/__init__.py
chatmof/agents/agent.py
chatmof/agents/prompt.py
chatmof/cli/__init__.py
chatmof/cli/install_griday.py
chatmof/cli/main.py
chatmof/cli/run.py
chatmof/cli/setup.py
chatmof/database/__init__.py
chatmof/database/load_model/__init__.py
chatmof/database/structures/__init__.py
chatmof/database/structures/coremof/__init__.py
chatmof/database/tables/__init__.py
chatmof/database/tables/coremof.xlsx
chatmof/llm/__init__.py
chatmof/llm/codellama.py
chatmof/llm/llama.py
chatmof/llm/openai.py
chatmof/llm/utils.py
chatmof/tools/__init__.py
chatmof/tools/tool_utils.py
chatmof/tools/ase_repl/__init__.py
chatmof/tools/ase_repl/base.py
chatmof/tools/ase_repl/prompt.py
chatmof/tools/ase_repl/tool.py
chatmof/tools/genetic_algorithm/__init__.py
chatmof/tools/genetic_algorithm/base.py
chatmof/tools/genetic_algorithm/cif_generate.py
chatmof/tools/genetic_algorithm/genetic_algorithm.py
chatmof/tools/genetic_algorithm/prompt.py
chatmof/tools/genetic_algorithm/tool.py
chatmof/tools/predictor/__init__.py
chatmof/tools/predictor/base.py
chatmof/tools/predictor/dataset.py
chatmof/tools/predictor/prompt.py
chatmof/tools/predictor/runner.py
chatmof/tools/predictor/tool.py
chatmof/tools/predictor/utils.py
chatmof/tools/python_repl/__init__.py
chatmof/tools/python_repl/base.py
chatmof/tools/python_repl/tool.py
chatmof/tools/search_csv/__init__.py
chatmof/tools/search_csv/base.py
chatmof/tools/search_csv/prompt.py
chatmof/tools/search_csv/tool.py
chatmof/tools/unit_converter/__init__.py
chatmof/tools/unit_converter/base.py
chatmof/tools/unit_converter/prompt.py
chatmof/tools/unit_converter/tool.py
chatmof/tools/visualizer/__init__.py
chatmof/tools/visualizer/base.py
chatmof/tools/visualizer/prompt.py
chatmof/tools/visualizer/tool.py
chatmof-0.2.2.dist-info/LICENSE
chatmof-0.2.2.dist-info/METADATA
chatmof-0.2.2.dist-info/WHEEL
chatmof-0.2.2.dist-info/entry_points.txt
chatmof-0.2.2.dist-info/top_level.txt
chatmof-0.2.2.dist-info/RECORD
