Metadata-Version: 2.1
Name: chatmof
Version: 0.2.2
Summary: chatmof
Download-URL: https://github.com/Yeonghun1675/ChatMOF
Author: Yeonghun Kang
Author-email: dudgns1675@kaist.ac.kr
Requires-Python: >=3.9
License-File: LICENSE
Requires-Dist: moftransformer (>=2.0)
Requires-Dist: pyyaml
Requires-Dist: urllib3 (<=1.25.11)
Requires-Dist: requests (<=2.27.1)
Requires-Dist: langchain (<=0.0.235)
Requires-Dist: transformers (>=4.34.1)
Requires-Dist: pormake
Requires-Dist: openai
Requires-Dist: openpyxl
Requires-Dist: tiktoken
Requires-Dist: google-api-python-client
Requires-Dist: wikipedia
Requires-Dist: timeout-decorator
Requires-Dist: numexpr
Requires-Dist: streamlit
Requires-Dist: bitsandbytes
Requires-Dist: accelerate
Requires-Dist: xformers
Requires-Dist: SentencePiece
Requires-Dist: openai (<1.0.0)
Provides-Extra: docs
Requires-Dist: sphinx ; extra == 'docs'
Requires-Dist: livereload ; extra == 'docs'
Requires-Dist: myst-parser ; extra == 'docs'
